[
	{
		"articleId": "WEB-CONTENT-01",
		"contentPath": "/journal-articles/journal_article_content_01.xml",
		"ddmStructureKey": "CLAIM",
		"ddmTemplateKey": "CLAIM-CARD",
		"folder": "Claims",
		"name": "Volkswagen Golf - CAU4536398"
	},
	{
		"articleId": "WEB-CONTENT-02",
		"contentPath": "/journal-articles/journal_article_content_02.xml",
		"ddmStructureKey": "CLAIM",
		"ddmTemplateKey": "CLAIM-CARD",
		"folder": "Claims",
		"name": "Sepulveda Blvd - CHM2546333"
	},
	{
		"articleId": "WEB-CONTENT-03",
		"contentPath": "/journal-articles/journal_article_content_03.xml",
		"ddmStructureKey": "CLAIM",
		"ddmTemplateKey": "CLAIM-CARD",
		"folder": "Claims",
		"name": "Volkswagen Golf - CAU5846990"
	},
	{
		"articleId": "WEB-CONTENT-04",
		"contentPath": "/journal-articles/journal_article_content_04.xml",
		"ddmStructureKey": "CLAIM",
		"ddmTemplateKey": "CLAIM-CARD",
		"folder": "Claims",
		"name": "David Aragonés - CHE3326955"
	},
	{
		"articleId": "WEB-CONTENT-05",
		"contentPath": "/journal-articles/journal_article_content_05.xml",
		"ddmStructureKey": "CLAIM",
		"ddmTemplateKey": "CLAIM-CARD",
		"folder": "Claims",
		"name": "Volkswagen Golf - CAU6821256"
	},
	{
		"articleId": "WEB-CONTENT-06",
		"contentPath": "/journal-articles/journal_article_content_06.xml",
		"ddmStructureKey": "CLAIM",
		"ddmTemplateKey": "CLAIM-CARD",
		"folder": "Claims",
		"name": "Sepulveda Blvd - CHM2371402"
	},
	{
		"articleId": "WEB-CONTENT-07",
		"contentPath": "/journal-articles/journal_article_content_07.xml",
		"ddmStructureKey": "CLAIM",
		"ddmTemplateKey": "CLAIM-CARD",
		"folder": "Claims",
		"name": "David Aragonés - CHL22214389"
	},
	{
		"articleId": "WEB-CONTENT-08",
		"contentPath": "/journal-articles/journal_article_content_08.xml",
		"ddmStructureKey": "CLAIM",
		"ddmTemplateKey": "CLAIM-CARD",
		"folder": "Claims",
		"name": "Sepulveda Blvd - CHM6821402"
	},
	{
		"articleId": "WEB-CONTENT-09",
		"contentPath": "/journal-articles/journal_article_content_09.xml",
		"ddmStructureKey": "POLICY",
		"ddmTemplateKey": "POLICY-CARD",
		"folder": "Policies",
		"name": "WK1774476306 - Liferay Employee"
	},
	{
		"articleId": "WEB-CONTENT-10",
		"contentPath": "/journal-articles/journal_article_content_10.xml",
		"ddmStructureKey": "POLICY",
		"ddmTemplateKey": "POLICY-CARD",
		"folder": "Policies",
		"name": "LF1774476306 - David Aragonés"
	},
	{
		"articleId": "WEB-CONTENT-11",
		"contentPath": "/journal-articles/journal_article_content_11.xml",
		"ddmStructureKey": "POLICY",
		"ddmTemplateKey": "POLICY-CARD",
		"folder": "Policies",
		"name": "HL1774476306 - David Aragonés"
	},
	{
		"articleId": "WEB-CONTENT-12",
		"contentPath": "/journal-articles/journal_article_content_12.xml",
		"ddmStructureKey": "POLICY",
		"ddmTemplateKey": "POLICY-CARD",
		"folder": "Policies",
		"name": "AU1774476306 - Volkswagen Golf 1.6"
	},
	{
		"articleId": "WEB-CONTENT-13",
		"contentPath": "/journal-articles/journal_article_content_13.xml",
		"ddmStructureKey": "POLICY",
		"ddmTemplateKey": "POLICY-CARD",
		"folder": "Policies",
		"name": "HM1774476306 - Sepulveda Blvd"
	}
]